pavi/__init__.py
pavi-0.0.1.dist-info/LICENSE
pavi-0.0.1.dist-info/METADATA
pavi-0.0.1.dist-info/WHEEL
pavi-0.0.1.dist-info/top_level.txt
pavi-0.0.1.dist-info/RECORD
