Metadata-Version: 2.1
Name: pavi
Version: 0.0.1
Summary: pavi sdk
Home-page: UNKNOWN
Author: Autolink
Author-email: yewentao@sensetime.com
License: UNKNOWN
Platform: UNKNOWN
Classifier: Programming Language :: Python :: 3
Classifier: License :: OSI Approved :: MIT License
Classifier: Operating System :: OS Independent
